auto_doraemon/__init__.py
auto_doraemon/user_defined_exception/__init__.py
auto_doraemon/user_defined_exception/auto_exception.py
auto_doraemon/util/__init__.py
auto_doraemon/util/excel_util.py
auto_doraemon/util/file_util.py
auto_doraemon/util/json_util.py
auto_doraemon/util/time_util.py
autodoraemon-1.0.8.dist-info/METADATA
autodoraemon-1.0.8.dist-info/WHEEL
autodoraemon-1.0.8.dist-info/top_level.txt
autodoraemon-1.0.8.dist-info/RECORD
