Metadata-Version: 2.1
Name: autodoraemon
Version: 1.0.8
Summary: 自动化测试辅助测试项目，主要提供工具函数
Home-page: UNKNOWN
Author: zhaojiajun
Author-email: zhaojiajun@baicizhan.com
License: UNKNOWN
Platform: UNKNOWN
Requires-Dist: setuptools (==47.1.0)
Requires-Dist: requests (==2.25.1)
Requires-Dist: xlrd (==2.0.1)
Requires-Dist: deepdiff (==5.8.1)
